snakefood3/__init__.py
snakefood3/__main__.py
snakefood3/gen_deps.py
snakefood3/graph.py
snakefood3-0.0.7.dist-info/entry_points.txt
snakefood3-0.0.7.dist-info/WHEEL
snakefood3-0.0.7.dist-info/METADATA
snakefood3-0.0.7.dist-info/RECORD
