Metadata-Version: 2.1
Name: snakefood3
Version: 0.0.7
Summary: Dependency Graphing for Python3
Home-page: https://github.com/Trim21/snakefood3
License: GPL
Keywords: snakefood,snakefood3,dependency graph
Author: Trim21
Author-email: trim21me@gmail.com
Requires-Python: >=3.7,<4.0
Classifier: License :: Other/Proprietary License
Classifier: Programming Language :: Python :: 3
Classifier: Programming Language :: Python :: 3.10
Classifier: Programming Language :: Python :: 3.7
Classifier: Programming Language :: Python :: 3.8
Classifier: Programming Language :: Python :: 3.9
Requires-Dist: Jinja2 (>=3.1.2,<4.0.0)
Project-URL: Repository, https://github.com/Trim21/snakefood3
